values.py
helm_values-0.1.7.dist-info/METADATA
helm_values-0.1.7.dist-info/WHEEL
helm_values-0.1.7.dist-info/top_level.txt
helm_values-0.1.7.dist-info/RECORD
