Metadata-Version: 2.4
Name: helm-values
Version: 0.1.7
Summary: Load and merge Helm values files for cdk8s
Author: fluffyspike
Requires-Python: >=3
Requires-Dist: pyyaml
Dynamic: author
Dynamic: description
Dynamic: description-content-type
Dynamic: requires-dist
Dynamic: requires-python
Dynamic: summary
